{
  "ts": "2025-09-09T19:13:12.735Z",
  "source": "scrape+fallback",
  "totals": 30,
  "results": [
    {
      "key": "electronics",
      "count": 10,
      "status": "fresh",
      "items": [
        {
          "rank": 1,
          "asin": "B08JHCVHTY",
          "title": "ASIN B08JHCVHTY",
          "url": "https://www.amazon.com/dp/B08JHCVHTY"
        },
        {
          "rank": 2,
          "asin": "B0CWXNS552",
          "title": "ASIN B0CWXNS552",
          "url": "https://www.amazon.com/dp/B0CWXNS552"
        },
        {
          "rank": 3,
          "asin": "B0CQMRKRV5",
          "title": "ASIN B0CQMRKRV5",
          "url": "https://www.amazon.com/dp/B0CQMRKRV5"
        },
        {
          "rank": 4,
          "asin": "B0D54JZTHY",
          "title": "ASIN B0D54JZTHY",
          "url": "https://www.amazon.com/dp/B0D54JZTHY"
        },
        {
          "rank": 5,
          "asin": "B0D1XD1ZV3",
          "title": "ASIN B0D1XD1ZV3",
          "url": "https://www.amazon.com/dp/B0D1XD1ZV3"
        },
        {
          "rank": 6,
          "asin": "B0CJM1GNFQ",
          "title": "ASIN B0CJM1GNFQ",
          "url": "https://www.amazon.com/dp/B0CJM1GNFQ"
        },
        {
          "rank": 7,
          "asin": "B0DCH8VDXF",
          "title": "ASIN B0DCH8VDXF",
          "url": "https://www.amazon.com/dp/B0DCH8VDXF"
        },
        {
          "rank": 8,
          "asin": "B08R6S1M1K",
          "title": "ASIN B08R6S1M1K",
          "url": "https://www.amazon.com/dp/B08R6S1M1K"
        },
        {
          "rank": 9,
          "asin": "B0DXXYS4BJ",
          "title": "ASIN B0DXXYS4BJ",
          "url": "https://www.amazon.com/dp/B0DXXYS4BJ"
        },
        {
          "rank": 10,
          "asin": "B0DGHMNQ5Z",
          "title": "ASIN B0DGHMNQ5Z",
          "url": "https://www.amazon.com/dp/B0DGHMNQ5Z"
        }
      ]
    },
    {
      "key": "home_garden",
      "count": 10,
      "status": "fresh",
      "items": [
        {
          "rank": 1,
          "asin": "B0BZYCJK89",
          "title": "ASIN B0BZYCJK89",
          "url": "https://www.amazon.com/dp/B0BZYCJK89"
        },
        {
          "rank": 2,
          "asin": "B01M16WBW1",
          "title": "ASIN B01M16WBW1",
          "url": "https://www.amazon.com/dp/B01M16WBW1"
        },
        {
          "rank": 3,
          "asin": "B01M7S9C6N",
          "title": "ASIN B01M7S9C6N",
          "url": "https://www.amazon.com/dp/B01M7S9C6N"
        },
        {
          "rank": 4,
          "asin": "B0BQR2BQYZ",
          "title": "ASIN B0BQR2BQYZ",
          "url": "https://www.amazon.com/dp/B0BQR2BQYZ"
        },
        {
          "rank": 5,
          "asin": "B00E4GACB8",
          "title": "ASIN B00E4GACB8",
          "url": "https://www.amazon.com/dp/B00E4GACB8"
        },
        {
          "rank": 6,
          "asin": "B08QRFZ6TH",
          "title": "ASIN B08QRFZ6TH",
          "url": "https://www.amazon.com/dp/B08QRFZ6TH"
        },
        {
          "rank": 7,
          "asin": "B07T869RNY",
          "title": "ASIN B07T869RNY",
          "url": "https://www.amazon.com/dp/B07T869RNY"
        },
        {
          "rank": 8,
          "asin": "B0C3FTCYZL",
          "title": "ASIN B0C3FTCYZL",
          "url": "https://www.amazon.com/dp/B0C3FTCYZL"
        },
        {
          "rank": 9,
          "asin": "B00NX0WXQI",
          "title": "ASIN B00NX0WXQI",
          "url": "https://www.amazon.com/dp/B00NX0WXQI"
        },
        {
          "rank": 10,
          "asin": "B0DR9PNXX3",
          "title": "ASIN B0DR9PNXX3",
          "url": "https://www.amazon.com/dp/B0DR9PNXX3"
        }
      ]
    },
    {
      "key": "beauty",
      "count": 10,
      "status": "fresh",
      "items": [
        {
          "rank": 1,
          "asin": "B074PVTPBW",
          "title": "ASIN B074PVTPBW",
          "url": "https://www.amazon.com/dp/B074PVTPBW"
        },
        {
          "rank": 2,
          "asin": "B07PBXXNCY",
          "title": "ASIN B07PBXXNCY",
          "url": "https://www.amazon.com/dp/B07PBXXNCY"
        },
        {
          "rank": 3,
          "asin": "B08KT2Z93D",
          "title": "ASIN B08KT2Z93D",
          "url": "https://www.amazon.com/dp/B08KT2Z93D"
        },
        {
          "rank": 4,
          "asin": "B09541P9WH",
          "title": "ASIN B09541P9WH",
          "url": "https://www.amazon.com/dp/B09541P9WH"
        },
        {
          "rank": 5,
          "asin": "B00U2VQZDS",
          "title": "ASIN B00U2VQZDS",
          "url": "https://www.amazon.com/dp/B00U2VQZDS"
        },
        {
          "rank": 6,
          "asin": "B00262227E",
          "title": "ASIN B00262227E",
          "url": "https://www.amazon.com/dp/B00262227E"
        },
        {
          "rank": 7,
          "asin": "B09V7Z4TJG",
          "title": "ASIN B09V7Z4TJG",
          "url": "https://www.amazon.com/dp/B09V7Z4TJG"
        },
        {
          "rank": 8,
          "asin": "B09542G9ZN",
          "title": "ASIN B09542G9ZN",
          "url": "https://www.amazon.com/dp/B09542G9ZN"
        },
        {
          "rank": 9,
          "asin": "B00T0C9XRK",
          "title": "ASIN B00T0C9XRK",
          "url": "https://www.amazon.com/dp/B00T0C9XRK"
        },
        {
          "rank": 10,
          "asin": "B081KL2QYJ",
          "title": "ASIN B081KL2QYJ",
          "url": "https://www.amazon.com/dp/B081KL2QYJ"
        }
      ]
    }
  ]
}